{"file":"CM-07.json","data":{"tipo":"CM","CM":"07","PR":"99","nombre":"Castilla - La Mancha","censo":75202,"escrutado_numero":61398,"escrutado_porcentaje":65,"votantes_numero":55959,"votantes_porcentaje":65,"abstencion_numero":13448,"abstencion_porcentaje":24,"grupos":[{"id":"0007","nombre":"PREPAL","votos":99231,"diputados":7670,"porcentaje":8},{"id":"0050","nombre":"ALTER","votos":98414,"diputados":59541,"porcentaje":8},{"id":"0003","nombre":"P.P.","votos":97853,"diputados":28915,"porcentaje":8},{"id":"0018","nombre":"ACNV-BAR-PRAO-R.E.P.O-UNIO","votos":96772,"diputados":7571,"porcentaje":8},{"id":"0038","nombre":"PARTIDO ANDALUCISTA","votos":96100,"diputados":2514,"porcentaje":8},{"id":"0017","nombre":"CEU","votos":94393,"diputados":48286,"porcentaje":8},{"id":"0021","nombre":"EXTREMADURA UNIDA","votos":87915,"diputados":24341,"porcentaje":7},{"id":"0186","nombre":"DISCAPACITADOS Y ENFERMEDADES RARAS","votos":85108,"diputados":68643,"porcentaje":7},{"id":"0049","nombre":"LPD","votos":81463,"diputados":77815,"porcentaje":7},{"id":"0025","nombre":"EB","votos":80757,"diputados":2994,"porcentaje":7},{"id":"0023","nombre":"PH","votos":78396,"diputados":29741,"porcentaje":7},{"id":"-1","nombre":"Blanco","votos":91126,"diputados":0,"porcentaje":8},{"id":"-2","nombre":"Nulos","votos":5394,"diputados":0,"porcentaje":0},{"id":"-3","nombre":"Otros","votos":104518,"diputados":1453994,"otros":[{"id":"0037","nombre":"P.C.P.E.","votos":7740,"diputados":36821},{"id":"0005","nombre":"M.C.R.","votos":7027,"diputados":58984},{"id":"0020","nombre":"I.Fem","votos":6740,"diputados":14521},{"id":"0067","nombre":"RECORTES CERO","votos":6288,"diputados":78243},{"id":"0002","nombre":"F.A.C.","votos":6224,"diputados":27434},{"id":"0048","nombre":"SAIn","votos":5914,"diputados":90883},{"id":"0056","nombre":"IPEX-PREX-CREX","votos":5350,"diputados":89182},{"id":"0009","nombre":"PT","votos":5191,"diputados":44233},{"id":"0058","nombre":"RRUE","votos":4907,"diputados":68672},{"id":"0047","nombre":"ImpulsoSocial","votos":4902,"diputados":81091},{"id":"0016","nombre":"P-LIB","votos":4582,"diputados":99603},{"id":"0133","nombre":"EPDD","votos":4311,"diputados":41884},{"id":"0022","nombre":"FE de las JONS","votos":3897,"diputados":77491},{"id":"0217","nombre":"IUCLM","votos":3471,"diputados":11615},{"id":"0157","nombre":"PRIMAVERA EUROPEA","votos":3272,"diputados":90088},{"id":"0053","nombre":"VOX","votos":3221,"diputados":24448},{"id":"0012","nombre":"PSOE","votos":3167,"diputados":77801},{"id":"0042","nombre":"PIRATAS","votos":2770,"diputados":28129},{"id":"0045","nombre":"PODEMOS","votos":2734,"diputados":27466},{"id":"0004","nombre":"UPyD","votos":2256,"diputados":66065},{"id":"0044","nombre":"LEM","votos":2172,"diputados":36546},{"id":"0041","nombre":"MOVIMIENTO RED","votos":2048,"diputados":31479},{"id":"0040","nombre":"M.S.R.","votos":1919,"diputados":1944},{"id":"0008","nombre":"PACMA","votos":1239,"diputados":73793},{"id":"0014","nombre":"CILUS","votos":929,"diputados":72687},{"id":"0039","nombre":"D.N.","votos":834,"diputados":12811},{"id":"0011","nombre":"C's","votos":772,"diputados":18284},{"id":"0028","nombre":"PARTIDO X","votos":641,"diputados":71796}],"porcentaje":9}]},"parent":{"id":"00","nombre":"Espa\u00f1a","json":"TO-00.json"},"children":[{"id":"02","nombre":"Albacete","json":"PR-02.json"},{"id":"13","nombre":"Ciudad Real","json":"PR-13.json"},{"id":"16","nombre":"Cuenca","json":"PR-16.json"},{"id":"19","nombre":"Guadalajara","json":"PR-19.json"},{"id":"45","nombre":"Toledo","json":"PR-45.json"}]}