{"file":"CM-14.json","data":{"tipo":"CM","CM":"14","PR":"99","nombre":"Pa\u00eds Vasco","censo":947,"escrutado_numero":19508,"escrutado_porcentaje":91,"votantes_numero":98149,"votantes_porcentaje":57,"abstencion_numero":26131,"abstencion_porcentaje":32,"grupos":[{"id":"0166","nombre":"EH Bildu","votos":99407,"diputados":91930,"porcentaje":9},{"id":"0003","nombre":"P.P.","votos":98263,"diputados":2552,"porcentaje":9},{"id":"0327","nombre":"EB","votos":97201,"diputados":37663,"porcentaje":8},{"id":"0005","nombre":"M.C.R.","votos":96455,"diputados":70169,"porcentaje":8},{"id":"0048","nombre":"SAIn","votos":95257,"diputados":32562,"porcentaje":8},{"id":"0053","nombre":"VOX","votos":93425,"diputados":6962,"porcentaje":8},{"id":"0372","nombre":"PODEMOS","votos":89051,"diputados":19680,"porcentaje":8},{"id":"0023","nombre":"PH","votos":84436,"diputados":41704,"porcentaje":7},{"id":"0138","nombre":"EPDD","votos":80529,"diputados":96734,"porcentaje":7},{"id":"0050","nombre":"ALTER","votos":75463,"diputados":82476,"porcentaje":7},{"id":"0039","nombre":"D.N.","votos":74508,"diputados":76109,"porcentaje":7},{"id":"-1","nombre":"Blanco","votos":23053,"diputados":0,"porcentaje":2},{"id":"-2","nombre":"Nulos","votos":20717,"diputados":0,"porcentaje":2},{"id":"-3","nombre":"Otros","votos":118276,"diputados":1442865,"otros":[{"id":"0014","nombre":"CILUS","votos":7186,"diputados":10515},{"id":"0190","nombre":"EAJ-PNV","votos":7068,"diputados":35181},{"id":"0018","nombre":"ACNV-BAR-PRAO-R.E.P.O-UNIO","votos":6852,"diputados":8195},{"id":"0041","nombre":"MOVIMIENTO RED","votos":6583,"diputados":79925},{"id":"0012","nombre":"PSOE","votos":6497,"diputados":91505},{"id":"0040","nombre":"M.S.R.","votos":6099,"diputados":65239},{"id":"0002","nombre":"F.A.C.","votos":6076,"diputados":58723},{"id":"0011","nombre":"C's","votos":5841,"diputados":56933},{"id":"0016","nombre":"P-LIB","votos":5807,"diputados":12781},{"id":"0044","nombre":"LEM","votos":5658,"diputados":99543},{"id":"0004","nombre":"UPyD","votos":5036,"diputados":25045},{"id":"0056","nombre":"IPEX-PREX-CREX","votos":4953,"diputados":57815},{"id":"0038","nombre":"PARTIDO ANDALUCISTA","votos":4886,"diputados":90433},{"id":"0165","nombre":"PRIMAVERA EUROPEA","votos":4121,"diputados":65075},{"id":"0047","nombre":"ImpulsoSocial","votos":4091,"diputados":38640},{"id":"0186","nombre":"DISCAPACITADOS Y ENFERMEDADES RARAS","votos":3936,"diputados":86357},{"id":"0042","nombre":"PIRATAS","votos":3675,"diputados":82167},{"id":"0021","nombre":"EXTREMADURA UNIDA","votos":3656,"diputados":51387},{"id":"0360","nombre":"R.R.U.E.","votos":3524,"diputados":33759},{"id":"0007","nombre":"PREPAL","votos":3369,"diputados":89723},{"id":"0009","nombre":"PT","votos":2664,"diputados":33535},{"id":"0028","nombre":"PARTIDO X","votos":2559,"diputados":74965},{"id":"0067","nombre":"RECORTES CERO","votos":2131,"diputados":6767},{"id":"0020","nombre":"I.Fem","votos":1936,"diputados":98959},{"id":"0305","nombre":"PACMA","votos":1911,"diputados":9683},{"id":"0220","nombre":"IU-EKI","votos":1140,"diputados":52793},{"id":"0022","nombre":"FE de las JONS","votos":592,"diputados":23040},{"id":"0037","nombre":"P.C.P.E.","votos":429,"diputados":4182}],"porcentaje":10}]},"parent":{"id":"00","nombre":"Espa\u00f1a","json":"TO-00.json"},"children":[{"id":"01","nombre":"Araba - \u00c1lava","json":"PR-01.json"},{"id":"20","nombre":"Gipuzkoa","json":"PR-20.json"},{"id":"48","nombre":"Bizkaia","json":"PR-48.json"}]}