{"file":"CM-11.json","data":{"tipo":"CM","CM":"11","PR":"99","nombre":"Galicia","censo":23890,"escrutado_numero":53427,"escrutado_porcentaje":72,"votantes_numero":35263,"votantes_porcentaje":59,"abstencion_numero":69675,"abstencion_porcentaje":30,"grupos":[{"id":"0058","nombre":"RRUE","votos":98193,"diputados":95096,"porcentaje":9},{"id":"0003","nombre":"P.P.","votos":96777,"diputados":58763,"porcentaje":9},{"id":"0028","nombre":"PARTIDO X","votos":95797,"diputados":9599,"porcentaje":8},{"id":"0188","nombre":"CxG","votos":85588,"diputados":30440,"porcentaje":8},{"id":"0044","nombre":"LEM","votos":85426,"diputados":37538,"porcentaje":8},{"id":"0007","nombre":"PREPAL","votos":85020,"diputados":59651,"porcentaje":8},{"id":"0186","nombre":"DISCAPACITADOS Y ENFERMEDADES RARAS","votos":84885,"diputados":72539,"porcentaje":8},{"id":"0021","nombre":"EXTREMADURA UNIDA","votos":83723,"diputados":35651,"porcentaje":7},{"id":"0005","nombre":"M.C.R.","votos":82182,"diputados":50949,"porcentaje":7},{"id":"0168","nombre":"BNG","votos":78287,"diputados":35682,"porcentaje":7},{"id":"0002","nombre":"F.A.C.","votos":76742,"diputados":75420,"porcentaje":7},{"id":"-1","nombre":"Blanco","votos":71245,"diputados":0,"porcentaje":6},{"id":"-2","nombre":"Nulos","votos":20532,"diputados":0,"porcentaje":2},{"id":"-3","nombre":"Otros","votos":85180,"diputados":1288160,"otros":[{"id":"0004","nombre":"UPyD","votos":7477,"diputados":40843},{"id":"0240","nombre":"PIRATAS","votos":6901,"diputados":81222},{"id":"0022","nombre":"FE de las JONS","votos":5767,"diputados":37034},{"id":"0009","nombre":"PT","votos":5690,"diputados":48392},{"id":"0018","nombre":"ACNV-BAR-PRAO-R.E.P.O-UNIO","votos":5376,"diputados":32157},{"id":"0040","nombre":"M.S.R.","votos":5352,"diputados":91831},{"id":"0039","nombre":"D.N.","votos":4714,"diputados":53893},{"id":"0045","nombre":"PODEMOS","votos":4065,"diputados":23379},{"id":"0303","nombre":"PACMA","votos":3634,"diputados":18636},{"id":"0067","nombre":"RECORTES CERO","votos":3324,"diputados":71737},{"id":"0050","nombre":"ALTER","votos":3301,"diputados":62212},{"id":"0056","nombre":"IPEX-PREX-CREX","votos":3074,"diputados":79415},{"id":"0020","nombre":"I.Fem","votos":2976,"diputados":24152},{"id":"0023","nombre":"PH","votos":2519,"diputados":37914},{"id":"0037","nombre":"P.C.P.E.","votos":2401,"diputados":54445},{"id":"0151","nombre":"PRIMAVERA EUROPEA","votos":2282,"diputados":47243},{"id":"0135","nombre":"EPDD","votos":2230,"diputados":9378},{"id":"0012","nombre":"PSOE","votos":2165,"diputados":72697},{"id":"0053","nombre":"VOX","votos":2156,"diputados":33516},{"id":"0038","nombre":"PARTIDO ANDALUCISTA","votos":1771,"diputados":39636},{"id":"0016","nombre":"P-LIB","votos":1538,"diputados":51315},{"id":"0041","nombre":"MOVIMIENTO RED","votos":1354,"diputados":67142},{"id":"0048","nombre":"SAIn","votos":1353,"diputados":14563},{"id":"0202","nombre":"AGE","votos":1338,"diputados":21359},{"id":"0326","nombre":"EB (326)","votos":1137,"diputados":5001},{"id":"0047","nombre":"ImpulsoSocial","votos":890,"diputados":2767},{"id":"0014","nombre":"CILUS","votos":282,"diputados":84255},{"id":"0011","nombre":"C's","votos":113,"diputados":82026}],"porcentaje":8}]},"parent":{"id":"00","nombre":"Espa\u00f1a","json":"TO-00.json"},"children":[{"id":"15","nombre":"A Coru\u00f1a","json":"PR-15.json"},{"id":"27","nombre":"Lugo","json":"PR-27.json"},{"id":"32","nombre":"Ourense","json":"PR-32.json"},{"id":"36","nombre":"Pontevedra","json":"PR-36.json"}]}