{"file":"MU-004.json","data":{"tipo":"MU","CM":"17","PR":"46","nombre":"Agullent","censo":12680,"escrutado_numero":9452,"escrutado_porcentaje":14,"votantes_numero":57297,"votantes_porcentaje":0,"abstencion_numero":70226,"abstencion_porcentaje":75,"grupos":[{"id":"0047","nombre":"ImpulsoSocial","votos":89354,"diputados":77631,"porcentaje":25},{"id":"0002","nombre":"F.A.C.","votos":72292,"diputados":4195,"porcentaje":21},{"id":"0038","nombre":"PARTIDO ANDALUCISTA","votos":47337,"diputados":4200,"porcentaje":13},{"id":"0039","nombre":"D.N.","votos":47079,"diputados":66729,"porcentaje":13},{"id":"0186","nombre":"DISCAPACITADOS Y ENFERMEDADES RARAS","votos":26630,"diputados":2100,"porcentaje":8},{"id":"0050","nombre":"ALTER","votos":11692,"diputados":80147,"porcentaje":3},{"id":"0053","nombre":"VOX","votos":3272,"diputados":69949,"porcentaje":1},{"id":"-1","nombre":"Blanco","votos":10614,"diputados":0,"porcentaje":3},{"id":"-2","nombre":"Nulos","votos":43191,"diputados":0,"porcentaje":12},{"id":"-3","nombre":"Otros","votos":0,"diputados":0,"otros":[],"porcentaje":0}]},"children":[],"parent":{"id":"46","nombre":"Valencia \/ Val\u00e8ncia","json":"PR-46.json"}}