{"file":"MU-042.json","data":{"tipo":"MU","CM":"17","PR":"46","nombre":"Aielo de Malferit","censo":57092,"escrutado_numero":77339,"escrutado_porcentaje":84,"votantes_numero":55970,"votantes_porcentaje":25,"abstencion_numero":37152,"abstencion_porcentaje":30,"grupos":[{"id":"0050","nombre":"ALTER","votos":87190,"diputados":26928,"porcentaje":16},{"id":"0047","nombre":"ImpulsoSocial","votos":77468,"diputados":13045,"porcentaje":15},{"id":"0039","nombre":"D.N.","votos":70677,"diputados":20649,"porcentaje":13},{"id":"0053","nombre":"VOX","votos":59904,"diputados":24266,"porcentaje":11},{"id":"0002","nombre":"F.A.C.","votos":58926,"diputados":87329,"porcentaje":11},{"id":"0038","nombre":"PARTIDO ANDALUCISTA","votos":55581,"diputados":70224,"porcentaje":11},{"id":"0186","nombre":"DISCAPACITADOS Y ENFERMEDADES RARAS","votos":49312,"diputados":44558,"porcentaje":9},{"id":"-1","nombre":"Blanco","votos":10262,"diputados":0,"porcentaje":2},{"id":"-2","nombre":"Nulos","votos":59753,"diputados":0,"porcentaje":11}]},"children":[],"parent":{"id":"46","nombre":"Valencia \/ Val\u00e8ncia","json":"PR-46.json"}}