{"file":"MU-117.json","data":{"tipo":"MU","CM":"17","PR":"46","nombre":"Emperador","censo":33869,"escrutado_numero":46983,"escrutado_porcentaje":59,"votantes_numero":58494,"votantes_porcentaje":100,"abstencion_numero":30512,"abstencion_porcentaje":55,"grupos":[{"id":"0039","nombre":"D.N.","votos":96985,"diputados":21850,"porcentaje":20},{"id":"0002","nombre":"F.A.C.","votos":89170,"diputados":80544,"porcentaje":18},{"id":"0050","nombre":"ALTER","votos":58146,"diputados":88310,"porcentaje":12},{"id":"0038","nombre":"PARTIDO ANDALUCISTA","votos":55064,"diputados":97522,"porcentaje":11},{"id":"0186","nombre":"DISCAPACITADOS Y ENFERMEDADES RARAS","votos":33751,"diputados":50725,"porcentaje":7},{"id":"0053","nombre":"VOX","votos":14739,"diputados":94572,"porcentaje":3},{"id":"0047","nombre":"ImpulsoSocial","votos":11338,"diputados":84109,"porcentaje":2},{"id":"-1","nombre":"Blanco","votos":37297,"diputados":0,"porcentaje":8},{"id":"-2","nombre":"Nulos","votos":95853,"diputados":0,"porcentaje":19},{"id":"-3","nombre":"Otros","votos":0,"diputados":0,"otros":[],"porcentaje":0}]},"children":[],"parent":{"id":"46","nombre":"Valencia \/ Val\u00e8ncia","json":"PR-46.json"}}