{"file":"MU-189.json","data":{"tipo":"MU","CM":"07","PR":"45","nombre":"Villamiel de Toledo","censo":38,"escrutado_numero":80,"escrutado_porcentaje":94,"votantes_numero":15,"votantes_porcentaje":73,"abstencion_numero":6,"abstencion_porcentaje":64,"grupos":[{"id":"0186","nombre":"DISCAPACITADOS Y ENFERMEDADES RARAS","votos":98,"porcentaje":26,"diputados":9},{"id":"0038","nombre":"PARTIDO ANDALUCISTA","votos":91,"porcentaje":33,"diputados":86},{"id":"0053","nombre":"VOX","votos":75,"porcentaje":3,"diputados":47},{"id":"0050","nombre":"ALTER","votos":65,"porcentaje":21,"diputados":1},{"id":"0002","nombre":"F.A.C.","votos":49,"porcentaje":39,"diputados":65},{"id":"0047","nombre":"ImpulsoSocial","votos":30,"porcentaje":67,"diputados":45},{"id":"0039","nombre":"D.N.","votos":29,"porcentaje":7,"diputados":68},{"id":"00","nombre":"Blanco","votos":79,"porcentaje":74,"diputados":0},{"id":"00","nombre":"Nulos","votos":25,"porcentaje":3,"diputados":0}]},"children":[],"parent":{"id":"45","nombre":"Toledo","json":"PR-45.json"}}