{"file":"MU-158.json","data":{"tipo":"MU","CM":"17","PR":"46","nombre":"Macastre","censo":804,"escrutado_numero":45577,"escrutado_porcentaje":24,"votantes_numero":37322,"votantes_porcentaje":4,"abstencion_numero":92626,"abstencion_porcentaje":92,"grupos":[{"id":"0039","nombre":"D.N.","votos":93758,"diputados":62263,"porcentaje":20},{"id":"0002","nombre":"F.A.C.","votos":87802,"diputados":71302,"porcentaje":19},{"id":"0053","nombre":"VOX","votos":60155,"diputados":78572,"porcentaje":13},{"id":"0047","nombre":"ImpulsoSocial","votos":52852,"diputados":86616,"porcentaje":11},{"id":"0050","nombre":"ALTER","votos":36369,"diputados":23130,"porcentaje":8},{"id":"0186","nombre":"DISCAPACITADOS Y ENFERMEDADES RARAS","votos":20525,"diputados":46732,"porcentaje":4},{"id":"0038","nombre":"PARTIDO ANDALUCISTA","votos":12088,"diputados":76850,"porcentaje":3},{"id":"-1","nombre":"Blanco","votos":6595,"diputados":0,"porcentaje":1},{"id":"-2","nombre":"Nulos","votos":90835,"diputados":0,"porcentaje":20},{"id":"-3","nombre":"Otros","votos":0,"diputados":0,"otros":[],"porcentaje":0}]},"children":[],"parent":{"id":"46","nombre":"Valencia \/ Val\u00e8ncia","json":"PR-46.json"}}