{"file":"MU-265.json","data":{"tipo":"MU","CM":"02","PR":"44","nombre":"Vinaceite","censo":99450,"escrutado_numero":3364,"escrutado_porcentaje":1,"votantes_numero":80000,"votantes_porcentaje":3,"abstencion_numero":80671,"abstencion_porcentaje":43,"grupos":[{"id":"0038","nombre":"PARTIDO ANDALUCISTA","votos":83487,"diputados":72336,"porcentaje":27},{"id":"0047","nombre":"ImpulsoSocial","votos":55926,"diputados":11042,"porcentaje":18},{"id":"0050","nombre":"ALTER","votos":37668,"diputados":36942,"porcentaje":12},{"id":"0186","nombre":"DISCAPACITADOS Y ENFERMEDADES RARAS","votos":28691,"diputados":67539,"porcentaje":9},{"id":"0053","nombre":"VOX","votos":10018,"diputados":43052,"porcentaje":3},{"id":"0039","nombre":"D.N.","votos":6650,"diputados":12041,"porcentaje":2},{"id":"0002","nombre":"F.A.C.","votos":4281,"diputados":21801,"porcentaje":1},{"id":"-1","nombre":"Blanco","votos":13461,"diputados":0,"porcentaje":4},{"id":"-2","nombre":"Nulos","votos":70011,"diputados":0,"porcentaje":23},{"id":"-3","nombre":"Otros","votos":0,"diputados":0,"otros":[],"porcentaje":0}]},"children":[],"parent":{"id":"44","nombre":"Teruel","json":"PR-44.json"}}