{"file":"MU-294.json","data":{"tipo":"MU","CM":"08","PR":"37","nombre":"Santa Marta de Tormes","censo":99509,"escrutado_numero":14941,"escrutado_porcentaje":19,"votantes_numero":30135,"votantes_porcentaje":99,"abstencion_numero":85609,"abstencion_porcentaje":11,"grupos":[{"id":"0047","nombre":"ImpulsoSocial","votos":55929,"diputados":17007,"porcentaje":20},{"id":"0038","nombre":"PARTIDO ANDALUCISTA","votos":47641,"diputados":66596,"porcentaje":17},{"id":"0050","nombre":"ALTER","votos":45861,"diputados":20719,"porcentaje":17},{"id":"0002","nombre":"F.A.C.","votos":39289,"diputados":78171,"porcentaje":14},{"id":"0039","nombre":"D.N.","votos":38791,"diputados":13298,"porcentaje":14},{"id":"0053","nombre":"VOX","votos":16878,"diputados":52526,"porcentaje":6},{"id":"0186","nombre":"DISCAPACITADOS Y ENFERMEDADES RARAS","votos":4287,"diputados":4744,"porcentaje":2},{"id":"-1","nombre":"Blanco","votos":22712,"diputados":0,"porcentaje":8},{"id":"-2","nombre":"Nulos","votos":5739,"diputados":0,"porcentaje":2}]},"children":[],"parent":{"id":"37","nombre":"Salamanca","json":"PR-37.json"}}