{"file":"MU-266.json","data":{"tipo":"MU","CM":"02","PR":"44","nombre":"Visiedo","censo":41142,"escrutado_numero":93078,"escrutado_porcentaje":25,"votantes_numero":84370,"votantes_porcentaje":10,"abstencion_numero":34551,"abstencion_porcentaje":26,"grupos":[{"id":"0047","nombre":"ImpulsoSocial","votos":88615,"diputados":42889,"porcentaje":22},{"id":"0186","nombre":"DISCAPACITADOS Y ENFERMEDADES RARAS","votos":56583,"diputados":75752,"porcentaje":14},{"id":"0002","nombre":"F.A.C.","votos":45555,"diputados":87930,"porcentaje":11},{"id":"0038","nombre":"PARTIDO ANDALUCISTA","votos":31692,"diputados":58526,"porcentaje":8},{"id":"0050","nombre":"ALTER","votos":29901,"diputados":52454,"porcentaje":7},{"id":"0053","nombre":"VOX","votos":16849,"diputados":55481,"porcentaje":4},{"id":"0039","nombre":"D.N.","votos":37,"diputados":17600,"porcentaje":0},{"id":"-1","nombre":"Blanco","votos":54158,"diputados":0,"porcentaje":13},{"id":"-2","nombre":"Nulos","votos":81748,"diputados":0,"porcentaje":20}]},"children":[],"parent":{"id":"44","nombre":"Teruel","json":"PR-44.json"}}