{"file":"MU-275.json","data":{"tipo":"MU","CM":"08","PR":"37","nombre":"Saldeana","censo":72055,"escrutado_numero":27762,"escrutado_porcentaje":58,"votantes_numero":98557,"votantes_porcentaje":31,"abstencion_numero":27639,"abstencion_porcentaje":16,"grupos":[{"id":"0050","nombre":"ALTER","votos":84402,"diputados":46732,"porcentaje":27},{"id":"0053","nombre":"VOX","votos":61889,"diputados":40697,"porcentaje":20},{"id":"0186","nombre":"DISCAPACITADOS Y ENFERMEDADES RARAS","votos":40449,"diputados":55338,"porcentaje":13},{"id":"0039","nombre":"D.N.","votos":27435,"diputados":37510,"porcentaje":9},{"id":"0038","nombre":"PARTIDO ANDALUCISTA","votos":18704,"diputados":91095,"porcentaje":6},{"id":"0002","nombre":"F.A.C.","votos":14405,"diputados":77171,"porcentaje":5},{"id":"0047","nombre":"ImpulsoSocial","votos":1493,"diputados":447,"porcentaje":0},{"id":"-1","nombre":"Blanco","votos":26439,"diputados":0,"porcentaje":8},{"id":"-2","nombre":"Nulos","votos":37202,"diputados":0,"porcentaje":12},{"id":"-3","nombre":"Otros","votos":0,"diputados":0,"otros":[],"porcentaje":0}]},"children":[],"parent":{"id":"37","nombre":"Salamanca","json":"PR-37.json"}}