{"file":"MU-395.json","data":{"tipo":"MU","CM":"08","PR":"09","nombre":"Tubilla del Agua","censo":65319,"escrutado_numero":79102,"escrutado_porcentaje":24,"votantes_numero":54568,"votantes_porcentaje":59,"abstencion_numero":55032,"abstencion_porcentaje":18,"grupos":[{"id":"0038","nombre":"PARTIDO ANDALUCISTA","votos":99585,"diputados":36809,"porcentaje":16},{"id":"0002","nombre":"F.A.C.","votos":96817,"diputados":90659,"porcentaje":15},{"id":"0047","nombre":"ImpulsoSocial","votos":96328,"diputados":6044,"porcentaje":15},{"id":"0053","nombre":"VOX","votos":77458,"diputados":97081,"porcentaje":12},{"id":"0039","nombre":"D.N.","votos":74367,"diputados":42812,"porcentaje":12},{"id":"0186","nombre":"DISCAPACITADOS Y ENFERMEDADES RARAS","votos":52651,"diputados":55560,"porcentaje":8},{"id":"0050","nombre":"ALTER","votos":21584,"diputados":9205,"porcentaje":3},{"id":"-1","nombre":"Blanco","votos":81798,"diputados":0,"porcentaje":13},{"id":"-2","nombre":"Nulos","votos":38533,"diputados":0,"porcentaje":6},{"id":"-3","nombre":"Otros","votos":0,"diputados":0,"otros":[],"porcentaje":0}]},"children":[],"parent":{"id":"09","nombre":"Burgos","json":"PR-09.json"}}