{"file":"MU-347.json","data":{"tipo":"MU","CM":"08","PR":"37","nombre":"La Vell\u00e9s","censo":60216,"escrutado_numero":57026,"escrutado_porcentaje":59,"votantes_numero":11854,"votantes_porcentaje":67,"abstencion_numero":8527,"abstencion_porcentaje":94,"grupos":[{"id":"0050","nombre":"ALTER","votos":88914,"diputados":89382,"porcentaje":17},{"id":"0053","nombre":"VOX","votos":80861,"diputados":29112,"porcentaje":16},{"id":"0002","nombre":"F.A.C.","votos":80041,"diputados":3081,"porcentaje":16},{"id":"0186","nombre":"DISCAPACITADOS Y ENFERMEDADES RARAS","votos":65706,"diputados":81951,"porcentaje":13},{"id":"0039","nombre":"D.N.","votos":63927,"diputados":27564,"porcentaje":12},{"id":"0038","nombre":"PARTIDO ANDALUCISTA","votos":22126,"diputados":74448,"porcentaje":4},{"id":"0047","nombre":"ImpulsoSocial","votos":14845,"diputados":3777,"porcentaje":3},{"id":"-1","nombre":"Blanco","votos":23024,"diputados":0,"porcentaje":4},{"id":"-2","nombre":"Nulos","votos":72678,"diputados":0,"porcentaje":14},{"id":"-3","nombre":"Otros","votos":0,"diputados":0,"otros":[],"porcentaje":0}]},"children":[],"parent":{"id":"37","nombre":"Salamanca","json":"PR-37.json"}}