{"file":"MU-379.json","data":{"tipo":"MU","CM":"08","PR":"37","nombre":"Zamay\u00f3n","censo":98,"escrutado_numero":36,"escrutado_porcentaje":85,"votantes_numero":6,"votantes_porcentaje":45,"abstencion_numero":86,"abstencion_porcentaje":14,"grupos":[{"id":"0038","nombre":"PARTIDO ANDALUCISTA","votos":63,"porcentaje":80,"diputados":9},{"id":"0186","nombre":"DISCAPACITADOS Y ENFERMEDADES RARAS","votos":61,"porcentaje":52,"diputados":90},{"id":"0050","nombre":"ALTER","votos":25,"porcentaje":73,"diputados":46},{"id":"0047","nombre":"ImpulsoSocial","votos":18,"porcentaje":58,"diputados":33},{"id":"0039","nombre":"D.N.","votos":11,"porcentaje":91,"diputados":0},{"id":"0002","nombre":"F.A.C.","votos":8,"porcentaje":88,"diputados":36},{"id":"0053","nombre":"VOX","votos":1,"porcentaje":34,"diputados":3},{"id":"00","nombre":"Blanco","votos":76,"porcentaje":45,"diputados":0},{"id":"00","nombre":"Nulos","votos":35,"porcentaje":17,"diputados":0}]},"children":[],"parent":{"id":"37","nombre":"Salamanca","json":"PR-37.json"}}