{"file":"MU-429.json","data":{"tipo":"MU","CM":"08","PR":"09","nombre":"Villaescusa la Sombr\u00eda","censo":2298,"escrutado_numero":7274,"escrutado_porcentaje":80,"votantes_numero":7117,"votantes_porcentaje":55,"abstencion_numero":8583,"abstencion_porcentaje":90,"grupos":[{"id":"0050","nombre":"ALTER","votos":9179,"diputados":6103,"porcentaje":17},{"id":"0002","nombre":"F.A.C.","votos":8617,"diputados":6050,"porcentaje":16},{"id":"0047","nombre":"ImpulsoSocial","votos":8167,"diputados":3371,"porcentaje":15},{"id":"0038","nombre":"PARTIDO ANDALUCISTA","votos":6135,"diputados":944,"porcentaje":11},{"id":"0186","nombre":"DISCAPACITADOS Y ENFERMEDADES RARAS","votos":2641,"diputados":3777,"porcentaje":5},{"id":"0039","nombre":"D.N.","votos":1855,"diputados":429,"porcentaje":3},{"id":"0053","nombre":"VOX","votos":682,"diputados":1533,"porcentaje":1},{"id":"-1","nombre":"Blanco","votos":8122,"diputados":0,"porcentaje":15},{"id":"-2","nombre":"Nulos","votos":9497,"diputados":0,"porcentaje":17},{"id":"-3","nombre":"Otros","votos":0,"diputados":0,"otros":[],"porcentaje":0}]},"children":[],"parent":{"id":"09","nombre":"Burgos","json":"PR-09.json"}}