{"file":"MU-902.json","data":{"tipo":"MU","CM":"09","PR":"43","nombre":"Sant Jaume d'Enveja","censo":70291,"escrutado_numero":73953,"escrutado_porcentaje":55,"votantes_numero":50454,"votantes_porcentaje":52,"abstencion_numero":46158,"abstencion_porcentaje":4,"grupos":[{"id":"0053","nombre":"VOX","votos":85611,"diputados":55920,"porcentaje":17},{"id":"0038","nombre":"PARTIDO ANDALUCISTA","votos":81129,"diputados":32000,"porcentaje":16},{"id":"0039","nombre":"D.N.","votos":79995,"diputados":60155,"porcentaje":16},{"id":"0186","nombre":"DISCAPACITADOS Y ENFERMEDADES RARAS","votos":67716,"diputados":16552,"porcentaje":14},{"id":"0050","nombre":"ALTER","votos":63175,"diputados":18529,"porcentaje":13},{"id":"0047","nombre":"ImpulsoSocial","votos":30635,"diputados":90548,"porcentaje":6},{"id":"0002","nombre":"F.A.C.","votos":20184,"diputados":15661,"porcentaje":4},{"id":"-1","nombre":"Blanco","votos":63714,"diputados":0,"porcentaje":13},{"id":"-2","nombre":"Nulos","votos":3373,"diputados":0,"porcentaje":1},{"id":"-3","nombre":"Otros","votos":0,"diputados":0,"otros":[],"porcentaje":0}]},"children":[],"parent":{"id":"43","nombre":"Tarragona","json":"PR-43.json"}}