{"file":"PR-26.json","data":{"tipo":"PR","CM":"16","PR":"26","nombre":"La Rioja","censo":234800,"escrutado_numero":234169,"escrutado_porcentaje":"099.73","votantes_numero":117196,"votantes_porcentaje":"050.05","abstencion_numero":116973,"abstencion_porcentaje":"049.95","grupos":[{"id":"0003","nombre":"P.P.","votos":43892,"porcentaje":"038.48","diputados":0},{"id":"0012","nombre":"PSOE","votos":27005,"porcentaje":"023.67","diputados":0},{"id":"0004","nombre":"UPyD","votos":10252,"porcentaje":"008.98","diputados":0},{"id":"0222","nombre":"IU-LV","votos":9261,"porcentaje":"008.11","diputados":0},{"id":"0045","nombre":"PODEMOS","votos":8536,"porcentaje":"007.48","diputados":0},{"id":"0011","nombre":"C's","votos":2572,"porcentaje":"002.25","diputados":0},{"id":"0053","nombre":"VOX","votos":1586,"porcentaje":"001.39","diputados":0},{"id":"0152","nombre":"PRIMAVERA EUROPEA","votos":1484,"porcentaje":"001.30","diputados":0},{"id":"0025","nombre":"EB","votos":936,"porcentaje":"000.82","diputados":0},{"id":"0041","nombre":"MOVIMIENTO RED","votos":859,"porcentaje":"000.75","diputados":0},{"id":"0008","nombre":"PACMA","votos":853,"porcentaje":"000.74","diputados":0},{"id":"-1","nombre":"Blanco","votos":3252,"porcentaje":"002.85","diputados":0},{"id":"-2","nombre":"Nulos","votos":3141,"porcentaje":"002.68","diputados":0},{"id":"-3","nombre":"Otros","votos":358,"porcentaje":"3","diputados":0,"otros":[{"id":"0028","nombre":"PARTIDO X","votos":63,"porcentaje":"000.55","diputados":0},{"id":"0037","nombre":"P.C.P.E.","votos":28,"porcentaje":"000.24","diputados":0},{"id":"0186","nombre":"DISCAPACITADOS Y ENFERMEDADES RARAS","votos":24,"porcentaje":"000.20","diputados":0},{"id":"0241","nombre":"PIRATAS","votos":23,"porcentaje":"000.20","diputados":0},{"id":"0049","nombre":"LPD","votos":21,"porcentaje":"000.18","diputados":0},{"id":"0047","nombre":"ImpulsoSocial","votos":21,"porcentaje":"000.18","diputados":0},{"id":"0067","nombre":"RECORTES CERO","votos":19,"porcentaje":"000.16","diputados":0},{"id":"0014","nombre":"CILUS","votos":17,"porcentaje":"000.14","diputados":0},{"id":"0020","nombre":"I.Fem","votos":16,"porcentaje":"000.14","diputados":0},{"id":"0022","nombre":"FE de las JONS","votos":14,"porcentaje":"000.12","diputados":0},{"id":"0017","nombre":"CEU","votos":14,"porcentaje":"000.12","diputados":0},{"id":"0002","nombre":"F.A.C.","votos":11,"porcentaje":"000.09","diputados":0},{"id":"0044","nombre":"LEM","votos":10,"porcentaje":"000.08","diputados":0},{"id":"0139","nombre":"EPDD","votos":8,"porcentaje":"000.07","diputados":0},{"id":"0039","nombre":"D.N.","votos":8,"porcentaje":"000.07","diputados":0},{"id":"0050","nombre":"ALTER","votos":8,"porcentaje":"000.06","diputados":0},{"id":"0040","nombre":"M.S.R.","votos":7,"porcentaje":"000.06","diputados":0},{"id":"0023","nombre":"PH","votos":6,"porcentaje":"000.05","diputados":0},{"id":"0016","nombre":"P-LIB","votos":6,"porcentaje":"000.05","diputados":0},{"id":"0058","nombre":"RRUE","votos":5,"porcentaje":"000.04","diputados":0},{"id":"0005","nombre":"M.C.R.","votos":5,"porcentaje":"000.03","diputados":0},{"id":"0018","nombre":"ACNV-BAR-PRAO-R.E.P.O-UNIO","votos":4,"porcentaje":"000.03","diputados":0},{"id":"0009","nombre":"PT","votos":4,"porcentaje":"000.03","diputados":0},{"id":"0007","nombre":"PREPAL","votos":4,"porcentaje":"000.03","diputados":0},{"id":"0021","nombre":"EXTREMADURA UNIDA","votos":4,"porcentaje":"000.03","diputados":0},{"id":"0048","nombre":"SAIn","votos":3,"porcentaje":"000.02","diputados":0},{"id":"0038","nombre":"PARTIDO ANDALUCISTA","votos":3,"porcentaje":"000.02","diputados":0},{"id":"0056","nombre":"IPEX-PREX-CREX","votos":2,"porcentaje":"000.01","diputados":0}]}]},"children":[],"parent":{"id":"16","nombre":"La Rioja","json":"CM-16.json"}}