{"file":"PR-41.json","data":{"tipo":"PR","CM":"01","PR":"41","nombre":"Sevilla","censo":1496295,"escrutado_numero":1470679,"escrutado_porcentaje":9829,"votantes_numero":663492,"votantes_porcentaje":4511,"abstencion_numero":807187,"abstencion_porcentaje":5489,"grupos":[{"id":"0012","nombre":"PSOE","votos":242941,"porcentaje":3730,"diputados":0},{"id":"0003","nombre":"P.P.","votos":143551,"porcentaje":2204,"diputados":0},{"id":"0211","nombre":"IULV-CA","votos":78759,"porcentaje":1209,"diputados":0},{"id":"0045","nombre":"PODEMOS","votos":50946,"porcentaje":782,"diputados":0},{"id":"0004","nombre":"UPyD","votos":48046,"porcentaje":737,"diputados":0},{"id":"0038","nombre":"PARTIDO ANDALUCISTA","votos":13299,"porcentaje":204,"diputados":0},{"id":"0011","nombre":"C's","votos":10837,"porcentaje":166,"diputados":0},{"id":"0053","nombre":"VOX","votos":7999,"porcentaje":122,"diputados":0},{"id":"0147","nombre":"PRIMAVERA EUROPEA","votos":7218,"porcentaje":110,"diputados":0},{"id":"0008","nombre":"PACMA","votos":6382,"porcentaje":97,"diputados":0},{"id":"0028","nombre":"PARTIDO X","votos":4921,"porcentaje":75,"diputados":0},{"id":"-1","nombre":"Blanco","votos":16952,"porcentaje":260,"diputados":0},{"id":"-2","nombre":"Nulos","votos":12189,"porcentaje":184,"diputados":0},{"id":"-3","nombre":"Otros","votos":1948,"porcentaje":285,"diputados":0,"otros":[{"id":"0041","nombre":"MOVIMIENTO RED","votos":408,"porcentaje":62,"diputados":0},{"id":"0025","nombre":"EB","votos":332,"porcentaje":51,"diputados":0},{"id":"0236","nombre":"PIRATAS","votos":110,"porcentaje":16,"diputados":0},{"id":"0186","nombre":"DISCAPACITADOS Y ENFERMEDADES RARAS","votos":104,"porcentaje":15,"diputados":0},{"id":"0067","nombre":"RECORTES CERO","votos":95,"porcentaje":14,"diputados":0},{"id":"0020","nombre":"I.Fem","votos":83,"porcentaje":12,"diputados":0},{"id":"0037","nombre":"P.C.P.E.","votos":82,"porcentaje":12,"diputados":0},{"id":"0022","nombre":"FE de las JONS","votos":79,"porcentaje":12,"diputados":0},{"id":"0047","nombre":"ImpulsoSocial","votos":67,"porcentaje":10,"diputados":0},{"id":"0014","nombre":"CILUS","votos":62,"porcentaje":9,"diputados":0},{"id":"0044","nombre":"LEM","votos":46,"porcentaje":7,"diputados":0},{"id":"0002","nombre":"F.A.C.","votos":46,"porcentaje":7,"diputados":0},{"id":"0049","nombre":"LPD","votos":45,"porcentaje":6,"diputados":0},{"id":"0023","nombre":"PH","votos":44,"porcentaje":6,"diputados":0},{"id":"0048","nombre":"SAIn","votos":40,"porcentaje":6,"diputados":0},{"id":"0016","nombre":"P-LIB","votos":32,"porcentaje":4,"diputados":0},{"id":"0040","nombre":"M.S.R.","votos":32,"porcentaje":4,"diputados":0},{"id":"0039","nombre":"D.N.","votos":30,"porcentaje":4,"diputados":0},{"id":"0058","nombre":"RRUE","votos":30,"porcentaje":4,"diputados":0},{"id":"0005","nombre":"M.C.R.","votos":28,"porcentaje":4,"diputados":0},{"id":"0050","nombre":"ALTER","votos":27,"porcentaje":4,"diputados":0},{"id":"0007","nombre":"PREPAL","votos":23,"porcentaje":3,"diputados":0},{"id":"0017","nombre":"CEU","votos":22,"porcentaje":3,"diputados":0},{"id":"0249","nombre":"PRAO","votos":20,"porcentaje":3,"diputados":0},{"id":"0125","nombre":"EPDD","votos":18,"porcentaje":2,"diputados":0},{"id":"0009","nombre":"PT","votos":16,"porcentaje":2,"diputados":0},{"id":"0021","nombre":"EXTREMADURA UNIDA","votos":15,"porcentaje":2,"diputados":0},{"id":"0056","nombre":"IPEX-PREX-CREX","votos":12,"porcentaje":1,"diputados":0}]}]},"parent":{"id":"01","nombre":"Andaluc\u00eda","json":"CM-01.json"}}