{"file":"PR-49.json","data":{"tipo":"PR","CM":"08","PR":"49","nombre":"Zamora","censo":8728,"escrutado_numero":761,"escrutado_porcentaje":35,"votantes_numero":2423,"votantes_porcentaje":93,"abstencion_numero":2524,"abstencion_porcentaje":3,"grupos":[{"id":"0218","nombre":"IUCyL","votos":9422,"diputados":1072,"porcentaje":5},{"id":"0186","nombre":"DISCAPACITADOS Y ENFERMEDADES RARAS","votos":9311,"diputados":2302,"porcentaje":5},{"id":"0045","nombre":"PODEMOS","votos":9293,"diputados":2924,"porcentaje":5},{"id":"0058","nombre":"RRUE","votos":9015,"diputados":7887,"porcentaje":5},{"id":"0003","nombre":"P.P.","votos":8832,"diputados":1326,"porcentaje":5},{"id":"0049","nombre":"LPD","votos":8501,"diputados":6406,"porcentaje":4},{"id":"0007","nombre":"PREPAL","votos":8366,"diputados":7238,"porcentaje":4},{"id":"0158","nombre":"PRIMAVERA EUROPEA","votos":7982,"diputados":9672,"porcentaje":4},{"id":"0004","nombre":"UPyD","votos":7928,"diputados":7120,"porcentaje":4},{"id":"0028","nombre":"PARTIDO X","votos":7842,"diputados":4561,"porcentaje":4},{"id":"-1","nombre":"Blanco","votos":287,"diputados":0,"porcentaje":0},{"id":"-2","nombre":"Nulos","votos":4166,"diputados":0,"porcentaje":2},{"id":"-3","nombre":"Otros","votos":102535,"diputados":156114,"otros":[{"id":"0067","nombre":"RECORTES CERO","votos":7144,"diputados":9270},{"id":"0132","nombre":"EPDD","votos":6984,"diputados":1872},{"id":"0053","nombre":"VOX","votos":6748,"diputados":1294},{"id":"0018","nombre":"ACNV-BAR-PRAO-R.E.P.O-UNIO","votos":6140,"diputados":285},{"id":"0044","nombre":"LEM","votos":5996,"diputados":7359},{"id":"0050","nombre":"ALTER","votos":5588,"diputados":6040},{"id":"0022","nombre":"FE de las JONS","votos":5338,"diputados":6516},{"id":"0002","nombre":"F.A.C.","votos":4460,"diputados":3805},{"id":"0009","nombre":"PT","votos":4219,"diputados":9481},{"id":"0021","nombre":"EXTREMADURA UNIDA","votos":4191,"diputados":837},{"id":"0023","nombre":"PH","votos":3910,"diputados":7702},{"id":"0016","nombre":"P-LIB","votos":3892,"diputados":7847},{"id":"0048","nombre":"SAIn","votos":3887,"diputados":9557},{"id":"0042","nombre":"PIRATAS","votos":3727,"diputados":3838},{"id":"0025","nombre":"EB","votos":3695,"diputados":8456},{"id":"0037","nombre":"P.C.P.E.","votos":3472,"diputados":4170},{"id":"0011","nombre":"C's","votos":3011,"diputados":5794},{"id":"0056","nombre":"IPEX-PREX-CREX","votos":2944,"diputados":1511},{"id":"0008","nombre":"PACMA","votos":2707,"diputados":1262},{"id":"0012","nombre":"PSOE","votos":2623,"diputados":5626},{"id":"0038","nombre":"PARTIDO ANDALUCISTA","votos":2199,"diputados":4425},{"id":"0014","nombre":"CILUS","votos":1967,"diputados":4303},{"id":"0039","nombre":"D.N.","votos":1920,"diputados":3037},{"id":"0047","nombre":"ImpulsoSocial","votos":1480,"diputados":8962},{"id":"0040","nombre":"M.S.R.","votos":1358,"diputados":8776},{"id":"0020","nombre":"I.Fem","votos":1099,"diputados":4043},{"id":"0017","nombre":"CEU","votos":1088,"diputados":5141},{"id":"0005","nombre":"M.C.R.","votos":473,"diputados":9344},{"id":"0041","nombre":"MOVIMIENTO RED","votos":275,"diputados":5561}],"porcentaje":53}]},"parent":{"id":"08","nombre":"Castilla y Le\u00f3n","json":"CM-08.json"}}