{"file":"PR-50.json","data":{"tipo":"PR","CM":"02","PR":"50","nombre":"Zaragoza","censo":6086,"escrutado_numero":77700,"escrutado_porcentaje":45,"votantes_numero":91671,"votantes_porcentaje":49,"abstencion_numero":18307,"abstencion_porcentaje":34,"grupos":[{"id":"0053","nombre":"VOX","votos":96784,"diputados":45532,"porcentaje":8},{"id":"0212","nombre":"IUA","votos":96436,"diputados":14707,"porcentaje":8},{"id":"0012","nombre":"PSOE","votos":89480,"diputados":14737,"porcentaje":8},{"id":"0237","nombre":"PIRATAS","votos":85631,"diputados":73931,"porcentaje":8},{"id":"0025","nombre":"EB","votos":85584,"diputados":71637,"porcentaje":7},{"id":"0056","nombre":"IPEX-PREX-CREX","votos":82376,"diputados":77703,"porcentaje":7},{"id":"0002","nombre":"F.A.C.","votos":80789,"diputados":27977,"porcentaje":7},{"id":"0048","nombre":"SAIn","votos":78904,"diputados":91123,"porcentaje":7},{"id":"0011","nombre":"C's","votos":75952,"diputados":85167,"porcentaje":7},{"id":"0041","nombre":"MOVIMIENTO RED","votos":75530,"diputados":12806,"porcentaje":7},{"id":"0058","nombre":"RRUE","votos":73409,"diputados":42169,"porcentaje":6},{"id":"-1","nombre":"Blanco","votos":54982,"diputados":0,"porcentaje":5},{"id":"-2","nombre":"Nulos","votos":65656,"diputados":0,"porcentaje":6},{"id":"-3","nombre":"Otros","votos":99623,"diputados":1622489,"otros":[{"id":"0186","nombre":"DISCAPACITADOS Y ENFERMEDADES RARAS","votos":6767,"diputados":42440},{"id":"0028","nombre":"PARTIDO X","votos":6165,"diputados":72406},{"id":"0037","nombre":"P.C.P.E.","votos":6147,"diputados":94508},{"id":"0067","nombre":"RECORTES CERO","votos":6024,"diputados":89746},{"id":"0003","nombre":"P.P.","votos":5672,"diputados":31018},{"id":"0021","nombre":"EXTREMADURA UNIDA","votos":5659,"diputados":63747},{"id":"0004","nombre":"UPyD","votos":5455,"diputados":53995},{"id":"0009","nombre":"PT","votos":5334,"diputados":81645},{"id":"0020","nombre":"I.Fem","votos":4995,"diputados":92255},{"id":"0156","nombre":"PRIMAVERA EUROPEA","votos":4892,"diputados":94167},{"id":"0014","nombre":"CILUS","votos":4665,"diputados":10248},{"id":"0016","nombre":"P-LIB","votos":4115,"diputados":46736},{"id":"0050","nombre":"ALTER","votos":4049,"diputados":32168},{"id":"0022","nombre":"FE de las JONS","votos":3779,"diputados":30633},{"id":"0126","nombre":"EPDD","votos":3741,"diputados":67669},{"id":"0045","nombre":"PODEMOS","votos":3538,"diputados":7803},{"id":"0023","nombre":"PH","votos":3439,"diputados":98323},{"id":"0040","nombre":"M.S.R.","votos":2787,"diputados":77280},{"id":"0005","nombre":"M.C.R.","votos":2272,"diputados":79243},{"id":"0038","nombre":"PARTIDO ANDALUCISTA","votos":1901,"diputados":95839},{"id":"0382","nombre":"BAR","votos":1637,"diputados":13165},{"id":"0008","nombre":"PACMA","votos":1432,"diputados":79526},{"id":"0047","nombre":"ImpulsoSocial","votos":1346,"diputados":45015},{"id":"0039","nombre":"D.N.","votos":1278,"diputados":53305},{"id":"0044","nombre":"LEM","votos":1228,"diputados":40377},{"id":"0017","nombre":"CEU","votos":1093,"diputados":73166},{"id":"0170","nombre":"Puyal\u00f3n","votos":175,"diputados":33841},{"id":"0007","nombre":"PREPAL","votos":38,"diputados":22225}],"porcentaje":9}]},"parent":{"id":"02","nombre":"Arag\u00f3n","json":"CM-02.json"}}