{"file":"TO-00.json","data":{"tipo":"TO","CM":"99","PR":"99","nombre":"Total Estatal","censo":57912,"escrutado_numero":46379,"escrutado_porcentaje":92,"votantes_numero":25198,"votantes_porcentaje":60,"abstencion_numero":77563,"abstencion_porcentaje":44,"grupos":[{"id":"0017","nombre":"CEU","votos":99255,"diputados":47160,"porcentaje":9},{"id":"0049","nombre":"LPD","votos":94860,"diputados":56559,"porcentaje":9},{"id":"0053","nombre":"VOX","votos":87574,"diputados":32949,"porcentaje":8},{"id":"0058","nombre":"RRUE","votos":85816,"diputados":19308,"porcentaje":8},{"id":"0040","nombre":"M.S.R.","votos":81444,"diputados":15310,"porcentaje":8},{"id":"0037","nombre":"P.C.P.E.","votos":75350,"diputados":61882,"porcentaje":7},{"id":"0045","nombre":"PODEMOS","votos":74939,"diputados":4041,"porcentaje":7},{"id":"0002","nombre":"F.A.C.","votos":74509,"diputados":71221,"porcentaje":7},{"id":"0044","nombre":"LEM","votos":67751,"diputados":92413,"porcentaje":6},{"id":"0012","nombre":"PSOE","votos":67684,"diputados":20800,"porcentaje":6},{"id":"0025","nombre":"EB","votos":67286,"diputados":13367,"porcentaje":6},{"id":"-1","nombre":"Blanco","votos":44909,"diputados":0,"porcentaje":4},{"id":"-2","nombre":"Nulos","votos":61153,"diputados":0,"porcentaje":6},{"id":"-3","nombre":"Otros","votos":94947,"diputados":1559676,"otros":[{"id":"0039","nombre":"D.N.","votos":6702,"diputados":62899},{"id":"0020","nombre":"I.Fem","votos":6698,"diputados":22034},{"id":"0018","nombre":"ACNV-BAR-PRAO-R.E.P.O-UNIO","votos":5999,"diputados":12841},{"id":"0028","nombre":"PARTIDO X","votos":5886,"diputados":74604},{"id":"0022","nombre":"FE de las JONS","votos":5498,"diputados":95846},{"id":"0042","nombre":"PIRATAS","votos":5386,"diputados":26613},{"id":"0021","nombre":"EXTREMADURA UNIDA","votos":5202,"diputados":61572},{"id":"0004","nombre":"UPyD","votos":4851,"diputados":91801},{"id":"0007","nombre":"PREPAL","votos":4583,"diputados":57552},{"id":"0047","nombre":"ImpulsoSocial","votos":4568,"diputados":71870},{"id":"0050","nombre":"ALTER","votos":4374,"diputados":62513},{"id":"0014","nombre":"CILUS","votos":4172,"diputados":96841},{"id":"0009","nombre":"PT","votos":3699,"diputados":71905},{"id":"0011","nombre":"C's","votos":3474,"diputados":62878},{"id":"0043","nombre":"EPDD","votos":3139,"diputados":46794},{"id":"0016","nombre":"P-LIB","votos":2816,"diputados":54549},{"id":"0055","nombre":"LA IZQUIERDA PLURAL (*)","votos":2517,"diputados":68602},{"id":"0008","nombre":"PACMA","votos":2278,"diputados":37307},{"id":"0041","nombre":"MOVIMIENTO RED","votos":2045,"diputados":85157},{"id":"0038","nombre":"PARTIDO ANDALUCISTA","votos":1944,"diputados":61072},{"id":"0023","nombre":"PH","votos":1823,"diputados":24434},{"id":"0048","nombre":"SAIn","votos":1706,"diputados":91975},{"id":"0056","nombre":"IPEX-PREX-CREX","votos":1540,"diputados":29599},{"id":"0052","nombre":"PRIMAVERA EUROPEA","votos":1190,"diputados":55222},{"id":"0067","nombre":"RECORTES CERO","votos":1116,"diputados":6214},{"id":"0186","nombre":"DISCAPACITADOS Y ENFERMEDADES RARAS","votos":904,"diputados":33371},{"id":"0003","nombre":"P.P.","votos":690,"diputados":63017},{"id":"0005","nombre":"M.C.R.","votos":147,"diputados":30594}],"porcentaje":9}]},"parent":[],"children":[{"id":"01","nombre":"Andaluc\u00eda","json":"CM-01.json"},{"id":"02","nombre":"Arag\u00f3n","json":"CM-02.json"},{"id":"03","nombre":"Principado de Asturias","json":"CM-03.json"},{"id":"04","nombre":"Illes Balears","json":"CM-04.json"},{"id":"05","nombre":"Canarias","json":"CM-05.json"},{"id":"06","nombre":"Cantabria","json":"CM-06.json"},{"id":"07","nombre":"Castilla - La Mancha","json":"CM-07.json"},{"id":"08","nombre":"Castilla y Le\u00f3n","json":"CM-08.json"},{"id":"09","nombre":"Catalunya","json":"CM-09.json"},{"id":"10","nombre":"Extremadura","json":"CM-10.json"},{"id":"11","nombre":"Galicia","json":"CM-11.json"},{"id":"12","nombre":"Comunidad de Madrid","json":"CM-12.json"},{"id":"13","nombre":"Comunidad Foral de Navarra","json":"CM-13.json"},{"id":"14","nombre":"Pa\u00eds Vasco","json":"CM-14.json"},{"id":"15","nombre":"Regi\u00f3n de Murcia","json":"CM-15.json"},{"id":"16","nombre":"La Rioja","json":"CM-16.json"},{"id":"17","nombre":"Comunitat Valenciana","json":"CM-17.json"},{"id":"18","nombre":"Ciudad de Ceuta","json":"CM-18.json"},{"id":"19","nombre":"Ciudad de Melilla","json":"CM-19.json"}]}